{"episodeStats":{"won":false,"actionCounts":{"DIRECT_FLIGHT":38,"DRIVE_FERRY":31,"DO_NOTHING":8,"CHARTER_FLIGHT":3}},"episodeResults":{"steps":[{"state":{"currentPlayer":0,"currentMovesLeft":4,"curedDiseases":[],"playerPosition":{"0":3,"1":3},"researchCenters":[3],"playerCards":{"0":[2,19,32,46],"1":[5,22,31,40]},"playedPlayerCards":[],"insufficientPlayerCards":false},"pValues":[0.1275,0.13125,0.1175,0.125,0.1125,0.13875,0.1325,0.115],"action":{"type":"DIRECT_FLIGHT","player":0,"from":3,"to":32,"card":32}},{"state":{"currentPlayer":0,"currentMovesLeft":3,"curedDiseases":[],"playerPosition":{"0":32,"1":3},"researchCenters":[3],"playerCards":{"0":[2,19,46],"1":[5,22,31,40]},"playedPlayerCards":[32],"insufficientPlayerCards":false},"pValues":[0.1445916114790287,0.152317880794702,0.1401766004415011,0.1401766004415011,0.11920529801324503,0.17218543046357615,0.13134657836644592],"action":{"type":"DIRECT_FLIGHT","player":0,"from":32,"to":2,"card":2}},{"state":{"currentPlayer":0,"currentMovesLeft":2,"curedDiseases":[],"playerPosition":{"0":2,"1":3},"researchCenters":[3],"playerCards":{"0":[19,46],"1":[5,22,31,40]},"playedPlayerCards":[2,32],"insufficientPlayerCards":false},"pValues":[0.1685022026431718,0.16519823788546256,0.14647577092511013,0.1696035242290749,0.21145374449339208,0.13876651982378854],"action":{"type":"DRIVE_FERRY","player":0,"from":2,"to":4}},{"state":{"currentPlayer":0,"currentMovesLeft":1,"curedDiseases":[],"playerPosition":{"0":4,"1":3},"researchCenters":[3],"playerCards":{"0":[19,46],"1":[5,22,31,40]},"playedPlayerCards":[2,32],"insufficientPlayerCards":false},"pValues":[0.13933547695605572,0.18220793140407288,0.14362272240085744,0.12754555198285103,0.13183279742765272,0.17470525187566988,0.1007502679528403],"action":{"type":"DO_NOTHING","player":0}},{"state":{"currentPlayer":1,"currentMovesLeft":4,"curedDiseases":[],"playerPosition":{"0":4,"1":3},"researchCenters":[3],"playerCards":{"0":[19,23,27,46],"1":[5,22,31,40]},"playedPlayerCards":[2,32],"insufficientPlayerCards":false},"pValues":[0.1325,0.1275,0.1175,0.13625,0.1175,0.1175,0.1375,0.11375],"action":{"type":"DIRECT_FLIGHT","player":1,"from":3,"to":31,"card":31}},{"state":{"currentPlayer":1,"currentMovesLeft":3,"curedDiseases":[],"playerPosition":{"0":4,"1":31},"researchCenters":[3],"playerCards":{"0":[19,23,27,46],"1":[5,22,40]},"playedPlayerCards":[2,31,32],"insufficientPlayerCards":false},"pValues":[0.17142857142857143,0.1813186813186813,0.17472527472527472,0.16043956043956045,0.16043956043956045,0.15164835164835164],"action":{"type":"DIRECT_FLIGHT","player":1,"from":31,"to":40,"card":40}},{"state":{"currentPlayer":1,"currentMovesLeft":2,"curedDiseases":[],"playerPosition":{"0":4,"1":40},"researchCenters":[3],"playerCards":{"0":[19,23,27,46],"1":[5,22]},"playedPlayerCards":[2,31,32,40],"insufficientPlayerCards":false},"pValues":[0.17590618336886993,0.1791044776119403,0.1812366737739872,0.1652452025586354,0.13752665245202558,0.16098081023454158],"action":{"type":"DRIVE_FERRY","player":1,"from":40,"to":37}},{"state":{"currentPlayer":1,"currentMovesLeft":1,"curedDiseases":[],"playerPosition":{"0":4,"1":37},"researchCenters":[3],"playerCards":{"0":[19,23,27,46],"1":[5,22]},"playedPlayerCards":[2,31,32,40],"insufficientPlayerCards":false},"pValues":[0.1384297520661157,0.10020661157024793,0.1353305785123967,0.13326446280991736,0.10640495867768596,0.16322314049586778,0.08677685950413223,0.13636363636363635],"action":{"type":"DRIVE_FERRY","player":1,"from":37,"to":38}},{"state":{"currentPlayer":0,"currentMovesLeft":4,"curedDiseases":[],"playerPosition":{"0":4,"1":38},"researchCenters":[3],"playerCards":{"0":[19,23,27,46],"1":[5,10,22,25]},"playedPlayerCards":[2,31,32,40],"insufficientPlayerCards":false},"pValues":[0.11125,0.1075,0.11375,0.10125,0.10375,0.13625,0.125,0.11,0.09125],"action":{"type":"DRIVE_FERRY","player":0,"from":4,"to":2}},{"state":{"currentPlayer":0,"currentMovesLeft":3,"curedDiseases":[],"playerPosition":{"0":2,"1":38},"researchCenters":[3],"playerCards":{"0":[19,23,27,46],"1":[5,10,22,25]},"playedPlayerCards":[2,31,32,40],"insufficientPlayerCards":false},"pValues":[0.12189616252821671,0.11738148984198646,0.12866817155756208,0.11963882618510158,0.16027088036117382,0.1309255079006772,0.12189616252821671,0.09932279909706546],"action":{"type":"DIRECT_FLIGHT","player":0,"from":2,"to":23,"card":23}},{"state":{"currentPlayer":0,"currentMovesLeft":2,"curedDiseases":[],"playerPosition":{"0":23,"1":38},"researchCenters":[3],"playerCards":{"0":[19,27,46],"1":[5,10,22,25]},"playedPlayerCards":[2,23,31,32,40],"insufficientPlayerCards":false},"pValues":[0.12554585152838427,0.12117903930131005,0.1299126637554585,0.12445414847161572,0.12117903930131005,0.15065502183406113,0.12554585152838427,0.10152838427947598],"action":{"type":"DO_NOTHING","player":0}},{"state":{"currentPlayer":0,"currentMovesLeft":1,"curedDiseases":[],"playerPosition":{"0":23,"1":38},"researchCenters":[3],"playerCards":{"0":[19,27,46],"1":[5,10,22,25]},"playedPlayerCards":[2,23,31,32,40],"insufficientPlayerCards":false},"pValues":[0.1377049180327869,0.13114754098360656,0.12240437158469945,0.10273224043715846,0.11584699453551912,0.13442622950819672,0.1726775956284153,0.08306010928961749],"action":{"type":"DRIVE_FERRY","player":0,"from":23,"to":20}},{"state":{"currentPlayer":1,"currentMovesLeft":4,"curedDiseases":[],"playerPosition":{"0":20,"1":38},"researchCenters":[3],"playerCards":{"0":[1,19,27,33,46],"1":[5,10,22,25]},"playedPlayerCards":[2,23,31,32,40],"insufficientPlayerCards":false},"pValues":[0.1125,0.1175,0.10875,0.1125,0.10875,0.1125,0.11,0.115,0.1025],"action":{"type":"DIRECT_FLIGHT","player":1,"from":38,"to":25,"card":25}},{"state":{"currentPlayer":1,"currentMovesLeft":3,"curedDiseases":[],"playerPosition":{"0":20,"1":25},"researchCenters":[3],"playerCards":{"0":[1,19,27,33,46],"1":[5,10,22]},"playedPlayerCards":[2,23,25,31,32,40],"insufficientPlayerCards":false},"pValues":[0.1235827664399093,0.13718820861678005,0.13151927437641722,0.12244897959183673,0.11791383219954649,0.10770975056689343,0.12585034013605442,0.13378684807256236],"action":{"type":"DIRECT_FLIGHT","player":1,"from":25,"to":10,"card":10}},{"state":{"currentPlayer":1,"currentMovesLeft":2,"curedDiseases":[],"playerPosition":{"0":20,"1":10},"researchCenters":[3],"playerCards":{"0":[1,19,27,33,46],"1":[5,22]},"playedPlayerCards":[2,10,23,25,31,32,40],"insufficientPlayerCards":false},"pValues":[0.16136114160263446,0.17453347969264543,0.16575192096597147,0.1712403951701427,0.15587266739846323,0.1712403951701427],"action":{"type":"DRIVE_FERRY","player":1,"from":10,"to":8}},{"state":{"currentPlayer":1,"currentMovesLeft":1,"curedDiseases":[],"playerPosition":{"0":20,"1":8},"researchCenters":[3],"playerCards":{"0":[1,19,27,33,46],"1":[5,22]},"playedPlayerCards":[2,10,23,25,31,32,40],"insufficientPlayerCards":false},"pValues":[0.14616193480546794,0.12723449001051526,0.13038906414300735,0.17139852786540483,0.12197686645636173,0.11146161934805468,0.19137749737118823],"action":{"type":"DRIVE_FERRY","player":1,"from":8,"to":6}},{"state":{"currentPlayer":0,"currentMovesLeft":4,"curedDiseases":[],"playerPosition":{"0":20,"1":6},"researchCenters":[3],"playerCards":{"0":[1,19,27,33,46],"1":[4,5,22,42]},"playedPlayerCards":[2,10,23,25,31,32,40],"insufficientPlayerCards":false},"pValues":[0.08739076154806492,0.0898876404494382,0.0986267166042447,0.07990012484394507,0.08114856429463171,0.07990012484394507,0.08489388264669163,0.11235955056179775,0.10362047440699126,0.09363295880149813,0.08863920099875156],"action":{"type":"DRIVE_FERRY","player":0,"from":20,"to":19}},{"state":{"currentPlayer":0,"currentMovesLeft":3,"curedDiseases":[],"playerPosition":{"0":19,"1":6},"researchCenters":[3],"playerCards":{"0":[1,19,27,33,46],"1":[4,5,22,42]},"playedPlayerCards":[2,10,23,25,31,32,40],"insufficientPlayerCards":false},"pValues":[0.015927189988623434,0.015927189988623434,0.01478953356086462,0.01478953356086462,0.01478953356086462,0.01478953356086462,0.013651877133105802,0.015927189988623434,0.017064846416382253,0.015927189988623434,0.01478953356086462,0.015927189988623434,0.015927189988623434,0.017064846416382253,0.01820250284414107,0.01820250284414107,0.01820250284414107,0.01820250284414107,0.017064846416382253,0.015927189988623434,0.017064846416382253,0.015927189988623434,0.017064846416382253,0.01820250284414107,0.017064846416382253,0.01820250284414107,0.01820250284414107,0.01820250284414107,0.017064846416382253,0.01820250284414107,0.017064846416382253,0.015927189988623434,0.017064846416382253,0.015927189988623434,0.019340159271899887,0.015927189988623434,0.015927189988623434,0.01820250284414107,0.01820250284414107,0.01820250284414107,0.017064846416382253,0.017064846416382253,0.015927189988623434,0.01820250284414107,0.017064846416382253,0.017064846416382253,0.015927189988623434,0.019340159271899887,0.01820250284414107,0.015927189988623434,0.019340159271899887,0.017064846416382253,0.017064846416382253,0.020477815699658702,0.017064846416382253,0.017064846416382253,0.015927189988623434,0.017064846416382253,0.017064846416382253],"action":{"type":"CHARTER_FLIGHT","player":0,"from":19,"to":28,"card":19}},{"state":{"currentPlayer":0,"currentMovesLeft":2,"curedDiseases":[],"playerPosition":{"0":28,"1":6},"researchCenters":[3],"playerCards":{"0":[1,27,33,46],"1":[4,5,22,42]},"playedPlayerCards":[2,10,19,23,25,31,32,40],"insufficientPlayerCards":false},"pValues":[0.11151960784313726,0.11029411764705882,0.11642156862745098,0.12377450980392157,0.1017156862745098,0.10294117647058823,0.12254901960784313,0.11029411764705882,0.10049019607843138],"action":{"type":"DIRECT_FLIGHT","player":0,"from":28,"to":1,"card":1}},{"state":{"currentPlayer":0,"currentMovesLeft":1,"curedDiseases":[],"playerPosition":{"0":1,"1":6},"researchCenters":[3],"playerCards":{"0":[27,33,46],"1":[4,5,22,42]},"playedPlayerCards":[1,2,10,19,23,25,31,32,40],"insufficientPlayerCards":false},"pValues":[0.09728506787330317,0.10067873303167421,0.13687782805429866,0.11312217194570136,0.08257918552036199,0.09615384615384616,0.1583710407239819,0.1244343891402715,0.09049773755656108],"action":{"type":"DRIVE_FERRY","player":0,"from":1,"to":36}},{"state":{"currentPlayer":1,"currentMovesLeft":4,"curedDiseases":[],"playerPosition":{"0":36,"1":6},"researchCenters":[3],"playerCards":{"0":[15,27,30,33,46],"1":[4,5,22,42]},"playedPlayerCards":[1,2,10,19,23,25,31,32,40],"insufficientPlayerCards":false},"pValues":[0.12125,0.11,0.11375,0.10875,0.11,0.1125,0.10625,0.1275,0.09],"action":{"type":"DRIVE_FERRY","player":1,"from":6,"to":9}},{"state":{"currentPlayer":1,"currentMovesLeft":3,"curedDiseases":[],"playerPosition":{"0":36,"1":9},"researchCenters":[3],"playerCards":{"0":[15,27,30,33,46],"1":[4,5,22,42]},"playedPlayerCards":[1,2,10,19,23,25,31,32,40],"insufficientPlayerCards":false},"pValues":[0.10146561443066517,0.09808342728297632,0.10484780157835401,0.0992108229988726,0.10372040586245772,0.10259301014656144,0.10935738444193913,0.09019165727170236,0.10033821871476889,0.09019165727170236],"action":{"type":"DRIVE_FERRY","player":1,"from":9,"to":12}},{"state":{"currentPlayer":1,"currentMovesLeft":2,"curedDiseases":[],"playerPosition":{"0":36,"1":12},"researchCenters":[3],"playerCards":{"0":[15,27,30,33,46],"1":[4,5,22,42]},"playedPlayerCards":[1,2,10,19,23,25,31,32,40],"insufficientPlayerCards":false},"pValues":[0.12134831460674157,0.11348314606741573,0.11797752808988764,0.12359550561797752,0.10337078651685393,0.11123595505617978,0.10337078651685393,0.11348314606741573,0.09213483146067415],"action":{"type":"DIRECT_FLIGHT","player":1,"from":12,"to":5,"card":5}},{"state":{"currentPlayer":1,"currentMovesLeft":1,"curedDiseases":[],"playerPosition":{"0":36,"1":5},"researchCenters":[3],"playerCards":{"0":[15,27,30,33,46],"1":[4,22,42]},"playedPlayerCards":[1,2,5,10,19,23,25,31,32,40],"insufficientPlayerCards":false},"pValues":[0.0930493273542601,0.1266816143497758,0.12331838565022421,0.1031390134529148,0.12780269058295965,0.13228699551569506,0.19282511210762332,0.10089686098654709],"action":{"type":"DIRECT_FLIGHT","player":1,"from":5,"to":4,"card":4}},{"state":{"currentPlayer":0,"currentMovesLeft":4,"curedDiseases":[],"playerPosition":{"0":36,"1":4},"researchCenters":[3],"playerCards":{"0":[15,27,30,33,46],"1":[11,22,28,42]},"playedPlayerCards":[1,2,4,5,10,19,23,25,31,32,40],"insufficientPlayerCards":false},"pValues":[0.10112359550561797,0.09987515605493133,0.09612983770287141,0.09488139825218476,0.09987515605493133,0.09363295880149813,0.10736579275905118,0.10861423220973783,0.10112359550561797,0.09737827715355805],"action":{"type":"DRIVE_FERRY","player":0,"from":36,"to":37}},{"state":{"currentPlayer":0,"currentMovesLeft":3,"curedDiseases":[],"playerPosition":{"0":37,"1":4},"researchCenters":[3],"playerCards":{"0":[15,27,30,33,46],"1":[11,22,28,42]},"playedPlayerCards":[1,2,4,5,10,19,23,25,31,32,40],"insufficientPlayerCards":false},"pValues":[0.09204545454545454,0.08977272727272727,0.08863636363636364,0.08636363636363636,0.09090909090909091,0.08977272727272727,0.0875,0.10227272727272728,0.08636363636363636,0.09772727272727273,0.08863636363636364],"action":{"type":"DIRECT_FLIGHT","player":0,"from":37,"to":27,"card":27}},{"state":{"currentPlayer":0,"currentMovesLeft":2,"curedDiseases":[],"playerPosition":{"0":27,"1":4},"researchCenters":[3],"playerCards":{"0":[15,30,33,46],"1":[11,22,28,42]},"playedPlayerCards":[1,2,4,5,10,19,23,25,27,31,32,40],"insufficientPlayerCards":false},"pValues":[0.09662921348314607,0.10112359550561797,0.09887640449438202,0.09213483146067415,0.09887640449438202,0.09438202247191012,0.09662921348314607,0.10112359550561797,0.1101123595505618,0.1101123595505618],"action":{"type":"DIRECT_FLIGHT","player":0,"from":27,"to":46,"card":46}},{"state":{"currentPlayer":0,"currentMovesLeft":1,"curedDiseases":[],"playerPosition":{"0":46,"1":4},"researchCenters":[3],"playerCards":{"0":[15,30,33],"1":[11,22,28,42]},"playedPlayerCards":[1,2,4,5,10,19,23,25,27,31,32,40,46],"insufficientPlayerCards":false},"pValues":[0.1603563474387528,0.15812917594654788,0.20935412026726058,0.15701559020044542,0.10579064587973273,0.20935412026726058],"action":{"type":"DRIVE_FERRY","player":0,"from":46,"to":45}},{"state":{"currentPlayer":1,"currentMovesLeft":4,"curedDiseases":[],"playerPosition":{"0":45,"1":4},"researchCenters":[3],"playerCards":{"0":[9,15,30,33,39],"1":[11,22,28,42]},"playedPlayerCards":[1,2,4,5,10,19,23,25,27,31,32,40,46],"insufficientPlayerCards":false},"pValues":[0.1111398976883983,0.11119936085974416,0.11116406211387972,0.11107710781937262,0.11106411695639731,0.1109251925761173,0.11118771745083678,0.1111398976883983,0.11110264684685543],"action":{"type":"DIRECT_FLIGHT","player":1,"from":4,"to":22,"card":22}},{"state":{"currentPlayer":1,"currentMovesLeft":3,"curedDiseases":[],"playerPosition":{"0":45,"1":22},"researchCenters":[3],"playerCards":{"0":[9,15,30,33,39],"1":[11,28,42]},"playedPlayerCards":[1,2,4,5,10,19,22,23,25,27,31,32,40,46],"insufficientPlayerCards":false},"pValues":[0.11116481556889088,0.11123725114346471,0.11120677745266631,0.11114323158522688,0.11114323158522688,0.11114323158522688,0.11094077812935738,0.11100420824453476,0.11101647470540543],"action":{"type":"DRIVE_FERRY","player":1,"from":22,"to":21}},{"state":{"currentPlayer":1,"currentMovesLeft":2,"curedDiseases":[],"playerPosition":{"0":45,"1":21},"researchCenters":[3],"playerCards":{"0":[9,15,30,33,39],"1":[11,28,42]},"playedPlayerCards":[1,2,4,5,10,19,22,23,25,27,31,32,40,46],"insufficientPlayerCards":false},"pValues":[0.14292868635819173,0.14311701570900798,0.14316275119134253,0.14277228761402705,0.14259684025479377,0.1427604397150276,0.14266197915760936],"action":{"type":"DIRECT_FLIGHT","player":1,"from":21,"to":42,"card":42}},{"state":{"currentPlayer":1,"currentMovesLeft":1,"curedDiseases":[],"playerPosition":{"0":45,"1":42},"researchCenters":[3],"playerCards":{"0":[9,15,30,33,39],"1":[11,28]},"playedPlayerCards":[1,2,4,5,10,19,22,23,25,27,31,32,40,42,46],"insufficientPlayerCards":false},"pValues":[0.20034656650201677,0.19989530653164908,0.20004265910070954,0.1993132382295999,0.2004022296360246],"action":{"type":"DIRECT_FLIGHT","player":1,"from":42,"to":28,"card":28}},{"state":{"currentPlayer":0,"currentMovesLeft":4,"curedDiseases":[],"playerPosition":{"0":45,"1":28},"researchCenters":[3],"playerCards":{"0":[9,15,30,33,39],"1":[0,11,16]},"playedPlayerCards":[1,2,4,5,10,19,22,23,25,27,28,31,32,40,42,46],"insufficientPlayerCards":false},"pValues":[0.09994170195667303,0.10006687044803204,0.10007857499346025,0.09988694068052319,0.09998090749276081,0.09970217865739195,0.09994170195667303,0.10006687044803204,0.10019910577455726,0.1001351475918964],"action":{"type":"DIRECT_FLIGHT","player":0,"from":45,"to":9,"card":9}},{"state":{"currentPlayer":0,"currentMovesLeft":3,"curedDiseases":[],"playerPosition":{"0":9,"1":28},"researchCenters":[3],"playerCards":{"0":[15,30,33,39],"1":[0,11,16]},"playedPlayerCards":[1,2,4,5,9,10,19,22,23,25,27,28,31,32,40,42,46],"insufficientPlayerCards":false},"pValues":[0.10003965859323674,0.10000536180155603,0.10003965859323674,0.09993306340877521,0.10001692391215013,0.09993306340877521,0.09985518441388085,0.0999454783846728,0.10021468357156617,0.10001692391215013],"action":{"type":"DO_NOTHING","player":0}},{"state":{"currentPlayer":0,"currentMovesLeft":2,"curedDiseases":[],"playerPosition":{"0":9,"1":28},"researchCenters":[3],"playerCards":{"0":[15,30,33,39],"1":[0,11,16]},"playedPlayerCards":[1,2,4,5,9,10,19,22,23,25,27,28,31,32,40,42,46],"insufficientPlayerCards":false},"pValues":[0.10004765015353395,0.09999237641638825,0.10000367574858625,0.09995769951696855,0.09993390177360523,0.09993390177360523,0.09988455385416269,0.10010005681343513,0.10012028177786422,0.10002590217185035],"action":{"type":"DRIVE_FERRY","player":0,"from":9,"to":8}},{"state":{"currentPlayer":0,"currentMovesLeft":1,"curedDiseases":[],"playerPosition":{"0":8,"1":28},"researchCenters":[3],"playerCards":{"0":[15,30,33,39],"1":[0,11,16]},"playedPlayerCards":[1,2,4,5,9,10,19,22,23,25,27,28,31,32,40,42,46],"insufficientPlayerCards":false},"pValues":[0.11115239418998069,0.11102429729232527,0.11126736112125235,0.11115239418998069,0.11089360648556673,0.11106070793186375,0.1108367400871065,0.11132544198533655,0.11128705671658759],"action":{"type":"DRIVE_FERRY","player":0,"from":8,"to":6}},{"state":{"currentPlayer":1,"currentMovesLeft":4,"curedDiseases":[],"playerPosition":{"0":6,"1":28},"researchCenters":[3],"playerCards":{"0":[15,18,30,33,34,39],"1":[0,11,16]},"playedPlayerCards":[1,2,4,5,9,10,19,22,23,25,27,28,31,32,40,42,46],"insufficientPlayerCards":false},"pValues":[0.1250393396367312,0.1250393396367312,0.12513290556947373,0.12502714117506702,0.12501482373726944,0.12493828356750418,0.12485679976241132,0.1249513669148119],"action":{"type":"DRIVE_FERRY","player":1,"from":28,"to":24}},{"state":{"currentPlayer":1,"currentMovesLeft":3,"curedDiseases":[],"playerPosition":{"0":6,"1":24},"researchCenters":[3],"playerCards":{"0":[15,18,30,33,34,39],"1":[0,11,16]},"playedPlayerCards":[1,2,4,5,9,10,19,22,23,25,27,28,31,32,40,42,46],"insufficientPlayerCards":false},"pValues":[0.11115717940165883,0.11124863055074141,0.11128700256548987,0.11104598510490987,0.11113580441759542,0.11108051532114199,0.11113580441759542,0.11093551646889835,0.11097356175196903],"action":{"type":"DRIVE_FERRY","player":1,"from":24,"to":25}},{"state":{"currentPlayer":1,"currentMovesLeft":2,"curedDiseases":[],"playerPosition":{"0":6,"1":25},"researchCenters":[3],"playerCards":{"0":[15,18,30,33,34,39],"1":[0,11,16]},"playedPlayerCards":[1,2,4,5,9,10,19,22,23,25,27,28,31,32,40,42,46],"insufficientPlayerCards":false},"pValues":[0.1250174239533823,0.12510296853452466,0.1250715642242474,0.1249837894741841,0.1250609202244988,0.12505018577636398,0.12478748729517095,0.12492566051762778],"action":{"type":"DO_NOTHING","player":1}},{"state":{"currentPlayer":1,"currentMovesLeft":1,"curedDiseases":[],"playerPosition":{"0":6,"1":25},"researchCenters":[3],"playerCards":{"0":[15,18,30,33,34,39],"1":[0,11,16]},"playedPlayerCards":[1,2,4,5,9,10,19,22,23,25,27,28,31,32,40,42,46],"insufficientPlayerCards":false},"pValues":[0.12495767477231691,0.1252708287502273,0.1251876200706411,0.1251971404496161,0.12483748829674676,0.12495767477231691,0.12470462774418552,0.12488694514394948],"action":{"type":"DIRECT_FLIGHT","player":1,"from":25,"to":16,"card":16}},{"state":{"currentPlayer":0,"currentMovesLeft":4,"curedDiseases":[],"playerPosition":{"0":6,"1":16},"researchCenters":[3],"playerCards":{"0":[15,18,30,33,34,39],"1":[0,11,29,38]},"playedPlayerCards":[1,2,4,5,9,10,16,19,22,23,25,27,28,31,32,40,42,46],"insufficientPlayerCards":false},"pValues":[0.0909133191402461,0.09093789512456504,0.0909256893316242,0.0908880673240583,0.09083537910398902,0.09093789512456504,0.09105178711276672,0.09087517609776544,0.09093789512456504,0.0908217204180897,0.09087517609776544],"action":{"type":"DRIVE_FERRY","player":0,"from":6,"to":9}},{"state":{"currentPlayer":0,"currentMovesLeft":3,"curedDiseases":[],"playerPosition":{"0":9,"1":16},"researchCenters":[3],"playerCards":{"0":[15,18,30,33,34,39],"1":[0,11,29,38]},"playedPlayerCards":[1,2,4,5,9,10,16,19,22,23,25,27,28,31,32,40,42,46],"insufficientPlayerCards":false},"pValues":[0.08332198154256716,0.08329817704348928,0.0833101634618129,0.083286017397304,0.083286017397304,0.08332198154256716,0.08337870433537457,0.08351046583575601,0.08338960438003094,0.08333363597151316,0.08319558972400752,0.08336766136827328],"action":{"type":"DIRECT_FLIGHT","player":0,"from":9,"to":18,"card":18}},{"state":{"currentPlayer":0,"currentMovesLeft":2,"curedDiseases":[],"playerPosition":{"0":18,"1":16},"researchCenters":[3],"playerCards":{"0":[15,30,33,34,39],"1":[0,11,29,38]},"playedPlayerCards":[1,2,4,5,9,10,16,18,19,22,23,25,27,28,31,32,40,42,46],"insufficientPlayerCards":false},"pValues":[0.09998306551997968,0.09997150732346792,0.10013236400804959,0.09993601705289967,0.09999449293340282,0.10000579250477133,0.09994798629794191,0.1001123388703061,0.09979403448695717,0.10012240100222393],"action":{"type":"DIRECT_FLIGHT","player":0,"from":18,"to":15,"card":15}},{"state":{"currentPlayer":0,"currentMovesLeft":1,"curedDiseases":[],"playerPosition":{"0":15,"1":16},"researchCenters":[3],"playerCards":{"0":[30,33,34,39],"1":[0,11,29,38]},"playedPlayerCards":[1,2,4,5,9,10,15,16,18,19,22,23,25,27,28,31,32,40,42,46],"insufficientPlayerCards":false},"pValues":[0.09993849034493968,0.09996228918100168,0.09999696767264808,0.10016415630051932,0.10005224394774619,0.09988914015963496,0.09990170578730885,0.10007353472732808,0.09981027046780201,0.10021120141107123],"action":{"type":"DIRECT_FLIGHT","player":0,"from":15,"to":39,"card":39}},{"state":{"currentPlayer":1,"currentMovesLeft":4,"curedDiseases":[],"playerPosition":{"0":39,"1":16},"researchCenters":[3],"playerCards":{"0":[14,30,33,34,35],"1":[0,11,29,38]},"playedPlayerCards":[1,2,4,5,9,10,15,16,18,19,22,23,25,27,28,31,32,39,40,42,46],"insufficientPlayerCards":false},"pValues":[0.09097418171135449,0.09087578853522067,0.09093850798470425,0.09080846727944833,0.0908886798483917,0.0908886798483917,0.09092630210950459,0.09100852214560072,0.09080846727944833,0.09101968966065263,0.09086271359728261],"action":{"type":"DRIVE_FERRY","player":1,"from":16,"to":15}},{"state":{"currentPlayer":1,"currentMovesLeft":3,"curedDiseases":[],"playerPosition":{"0":39,"1":15},"researchCenters":[3],"playerCards":{"0":[14,30,33,34,35],"1":[0,11,29,38]},"playedPlayerCards":[1,2,4,5,9,10,15,16,18,19,22,23,25,27,28,31,32,39,40,42,46],"insufficientPlayerCards":false},"pValues":[0.10006668712286929,0.10004493500300093,0.10004493500300093,0.10001140286829077,0.09996488836815498,0.09997671937058444,0.10008798097591005,0.09981091052258549,0.10008798097591005,0.09990355978969317],"action":{"type":"DRIVE_FERRY","player":1,"from":15,"to":16}},{"state":{"currentPlayer":1,"currentMovesLeft":2,"curedDiseases":[],"playerPosition":{"0":39,"1":16},"researchCenters":[3],"playerCards":{"0":[14,30,33,34,35],"1":[0,11,29,38]},"playedPlayerCards":[1,2,4,5,9,10,15,16,18,19,22,23,25,27,28,31,32,39,40,42,46],"insufficientPlayerCards":false},"pValues":[0.09095651397524807,0.09080566490863352,0.09095651397524807,0.09088995507549967,0.09084274115930425,0.09088995507549967,0.09090138864408331,0.09106727264620265,0.09078008775931612,0.09100851813688156,0.09090138864408331],"action":{"type":"DRIVE_FERRY","player":1,"from":16,"to":13}},{"state":{"currentPlayer":1,"currentMovesLeft":1,"curedDiseases":[],"playerPosition":{"0":39,"1":13},"researchCenters":[3],"playerCards":{"0":[14,30,33,34,35],"1":[0,11,29,38]},"playedPlayerCards":[1,2,4,5,9,10,15,16,18,19,22,23,25,27,28,31,32,39,40,42,46],"insufficientPlayerCards":false},"pValues":[0.10016822821252658,0.09973312554084386,0.09997393425063447,0.10006492369744824,0.10007574221717892,0.09991260012251296,0.09993758269646516,0.09973312554084386,0.10031429154200139,0.10008644617954444],"action":{"type":"DIRECT_FLIGHT","player":1,"from":13,"to":0,"card":0}},{"state":{"currentPlayer":0,"currentMovesLeft":4,"curedDiseases":[],"playerPosition":{"0":39,"1":0},"researchCenters":[3],"playerCards":{"0":[14,30,33,34,35],"1":[11,20,29,38,45]},"playedPlayerCards":[0,1,2,4,5,9,10,15,16,18,19,22,23,25,27,28,31,32,39,40,42,46],"insufficientPlayerCards":false},"pValues":[0.09095007497647006,0.09098529267106463,0.09092582341963022,0.09093802923057093,0.09088820135658318,0.09084897141490655,0.0908622352421758,0.09095007497647006,0.09098529267106463,0.09090091408934745,0.09076508995171655],"action":{"type":"DRIVE_FERRY","player":0,"from":39,"to":42}},{"state":{"currentPlayer":0,"currentMovesLeft":3,"curedDiseases":[],"playerPosition":{"0":42,"1":0},"researchCenters":[3],"playerCards":{"0":[14,30,33,34,35],"1":[11,20,29,38,45]},"playedPlayerCards":[0,1,2,4,5,9,10,15,16,18,19,22,23,25,27,28,31,32,39,40,42,46],"insufficientPlayerCards":false},"pValues":[0.12511672481517414,0.1251061668246067,0.1250520115751638,0.12496022275191603,0.12493619350986203,0.12514787969456254,0.12489926932493658,0.124781531503778],"action":{"type":"DIRECT_FLIGHT","player":0,"from":42,"to":35,"card":35}},{"state":{"currentPlayer":0,"currentMovesLeft":2,"curedDiseases":[],"playerPosition":{"0":35,"1":0},"researchCenters":[3],"playerCards":{"0":[14,30,33,34],"1":[11,20,29,38,45]},"playedPlayerCards":[0,1,2,4,5,9,10,15,16,18,19,22,23,25,27,28,31,32,35,39,40,42,46],"insufficientPlayerCards":false},"pValues":[0.11117862928467584,0.1111243982797005,0.1112303616324169,0.11111323046566901,0.1110196455089139,0.1110556608776012,0.11117862928467584,0.11104378378874565,0.1110556608776012],"action":{"type":"DIRECT_FLIGHT","player":0,"from":35,"to":34,"card":34}},{"state":{"currentPlayer":0,"currentMovesLeft":1,"curedDiseases":[],"playerPosition":{"0":34,"1":0},"researchCenters":[3],"playerCards":{"0":[14,30,33],"1":[11,20,29,38,45]},"playedPlayerCards":[0,1,2,4,5,9,10,15,16,18,19,22,23,25,27,28,31,32,34,35,39,40,42,46],"insufficientPlayerCards":false},"pValues":[0.16634240395048286,0.16699016496592264,0.16662265277254132,0.1666916241885679,0.16616723703051225,0.16718591709197314],"action":{"type":"DO_NOTHING","player":0}},{"state":{"currentPlayer":1,"currentMovesLeft":4,"curedDiseases":[],"playerPosition":{"0":34,"1":0},"researchCenters":[3],"playerCards":{"0":[6,14,26,30,33],"1":[11,20,29,38,45]},"playedPlayerCards":[0,1,2,4,5,9,10,15,16,18,19,22,23,25,27,28,31,32,34,35,39,40,42,46],"insufficientPlayerCards":false},"pValues":[0.10001223439436532,0.10001223439436532,0.10007215780883548,0.09997449657071907,0.09997449657071907,0.09998723315884946,0.09986636909911197,0.09999981112620415,0.09990828601550769,0.1001926808613225],"action":{"type":"DIRECT_FLIGHT","player":1,"from":0,"to":11,"card":11}},{"state":{"currentPlayer":1,"currentMovesLeft":3,"curedDiseases":[],"playerPosition":{"0":34,"1":11},"researchCenters":[3],"playerCards":{"0":[6,14,26,30,33],"1":[20,29,38,45]},"playedPlayerCards":[0,1,2,4,5,9,10,11,15,16,18,19,22,23,25,27,28,31,32,34,35,39,40,42,46],"insufficientPlayerCards":false},"pValues":[0.12505842753708213,0.12499083019599722,0.125112120446053,0.12489467295830549,0.12480406890879545,0.12491940783390099,0.12484369886678266,0.12537677325308302],"action":{"type":"DO_NOTHING","player":1}},{"state":{"currentPlayer":1,"currentMovesLeft":2,"curedDiseases":[],"playerPosition":{"0":34,"1":11},"researchCenters":[3],"playerCards":{"0":[6,14,26,30,33],"1":[20,29,38,45]},"playedPlayerCards":[0,1,2,4,5,9,10,11,15,16,18,19,22,23,25,27,28,31,32,34,35,39,40,42,46],"insufficientPlayerCards":false},"pValues":[0.12502005837865532,0.12494156930376679,0.12506281175138836,0.12500914000365468,0.1248202303499385,0.1249530852679774,0.12480742881930972,0.1253856761253092],"action":{"type":"DRIVE_FERRY","player":1,"from":11,"to":8}},{"state":{"currentPlayer":1,"currentMovesLeft":1,"curedDiseases":[],"playerPosition":{"0":34,"1":8},"researchCenters":[3],"playerCards":{"0":[6,14,26,30,33],"1":[20,29,38,45]},"playedPlayerCards":[0,1,2,4,5,9,10,11,15,16,18,19,22,23,25,27,28,31,32,34,35,39,40,42,46],"insufficientPlayerCards":false},"pValues":[0.11138258996007556,0.11093624566887071,0.11089639120752509,0.11141713532093446,0.11102407238849422,0.11093624566887071,0.11124268311237995,0.1110479520210561,0.1111166846517933],"action":{"type":"DIRECT_FLIGHT","player":1,"from":8,"to":45,"card":45}},{"state":{"currentPlayer":0,"currentMovesLeft":4,"curedDiseases":[],"playerPosition":{"0":34,"1":45},"researchCenters":[3],"playerCards":{"0":[6,14,26,30,33],"1":[17,20,29,38,44]},"playedPlayerCards":[0,1,2,4,5,9,10,11,15,16,18,19,22,23,25,27,28,31,32,34,35,39,40,42,45,46],"insufficientPlayerCards":false},"pValues":[0.12506083599284404,0.12494768963270018,0.12492110684308967,0.12488015214834018,0.12474864706546426,0.12538752550811536,0.1249344682311412,0.12511957457830514],"action":{"type":"DRIVE_FERRY","player":0,"from":34,"to":33}},{"state":{"currentPlayer":0,"currentMovesLeft":3,"curedDiseases":[],"playerPosition":{"0":33,"1":45},"researchCenters":[3],"playerCards":{"0":[6,14,26,30,33],"1":[17,20,29,38,44]},"playedPlayerCards":[0,1,2,4,5,9,10,11,15,16,18,19,22,23,25,27,28,31,32,34,35,39,40,42,45,46],"insufficientPlayerCards":false},"pValues":[0.017236861314695033,0.017236861314695033,0.017236861314695033,0.017236861314695033,0.017236861314695033,0.01721221286101534,0.01721221286101534,0.017258449019169595,0.01721221286101534,0.017236861314695033,0.017236861314695033,0.017247989320617045,0.017247989320617045,0.017236861314695033,0.017247989320617045,0.017247989320617045,0.017258449019169595,0.017224973210563568,0.017247989320617045,0.017258449019169595,0.017236861314695033,0.017258449019169595,0.017236861314695033,0.017224973210563568,0.017247989320617045,0.017247989320617045,0.017224973210563568,0.017247989320617045,0.017236861314695033,0.017236861314695033,0.017236861314695033,0.017247989320617045,0.017247989320617045,0.017247989320617045,0.017258449019169595,0.017247989320617045,0.017268316494659916,0.017236861314695033,0.017247989320617045,0.017247989320617045,0.017236861314695033,0.017236861314695033,0.017236861314695033,0.017236861314695033,0.017236861314695033,0.017224973210563568,0.017247989320617045,0.017236861314695033,0.017247989320617045,0.017236861314695033,0.017247989320617045,0.017247989320617045,0.017236861314695033,0.017247989320617045,0.017236861314695033,0.017236861314695033,0.017247989320617045,0.017258449019169595],"action":{"type":"CHARTER_FLIGHT","player":0,"from":33,"to":39,"card":33}},{"state":{"currentPlayer":0,"currentMovesLeft":2,"curedDiseases":[],"playerPosition":{"0":39,"1":45},"researchCenters":[3],"playerCards":{"0":[6,14,26,30],"1":[17,20,29,38,44]},"playedPlayerCards":[0,1,2,4,5,9,10,11,15,16,18,19,22,23,25,27,28,31,32,33,34,35,39,40,42,45,46],"insufficientPlayerCards":false},"pValues":[0.09998899048283456,0.10006132933707458,0.09991106790332299,0.10002580717934517,0.09991106790332299,0.09989747527576262,0.10004962680858726,0.09981183311773104,0.10031699481267381,0.10002580717934517],"action":{"type":"DIRECT_FLIGHT","player":0,"from":39,"to":26,"card":26}},{"state":{"currentPlayer":0,"currentMovesLeft":1,"curedDiseases":[],"playerPosition":{"0":26,"1":45},"researchCenters":[3],"playerCards":{"0":[6,14,30],"1":[17,20,29,38,44]},"playedPlayerCards":[0,1,2,4,5,9,10,11,15,16,18,19,22,23,25,26,27,28,31,32,33,34,35,39,40,42,45,46],"insufficientPlayerCards":false},"pValues":[0.14276890549257762,0.14280387533584832,0.14274511210704974,0.1433210484116468,0.14293584896159744,0.14279231267397488,0.14263289701730503],"action":{"type":"DRIVE_FERRY","player":0,"from":26,"to":27}},{"state":{"currentPlayer":1,"currentMovesLeft":4,"curedDiseases":[],"playerPosition":{"0":27,"1":45},"researchCenters":[3],"playerCards":{"0":[6,7,8,14,30],"1":[17,20,29,38,44]},"playedPlayerCards":[0,1,2,4,5,9,10,11,15,16,18,19,22,23,25,26,27,28,31,32,33,34,35,39,40,42,45,46],"insufficientPlayerCards":false},"pValues":[0.10009240821908726,0.100103848129669,0.10016989637322182,0.10000848442490386,0.1000453082992302,0.09976985739183915,0.09981628114242755,0.1001591834860941,0.10008083738239092,0.09975389515113617],"action":{"type":"DIRECT_FLIGHT","player":1,"from":45,"to":17,"card":17}},{"state":{"currentPlayer":1,"currentMovesLeft":3,"curedDiseases":[],"playerPosition":{"0":27,"1":17},"researchCenters":[3],"playerCards":{"0":[6,7,8,14,30],"1":[20,29,38,44]},"playedPlayerCards":[0,1,2,4,5,9,10,11,15,16,17,18,19,22,23,25,26,27,28,31,32,33,34,35,39,40,42,45,46],"insufficientPlayerCards":false},"pValues":[0.12513349432722143,0.12513349432722143,0.12516465338232757,0.1250576556103103,0.12465306252710653,0.12506877241363482,0.1249769712878449,0.1248118961243331],"action":{"type":"DRIVE_FERRY","player":1,"from":17,"to":18}},{"state":{"currentPlayer":1,"currentMovesLeft":2,"curedDiseases":[],"playerPosition":{"0":27,"1":18},"researchCenters":[3],"playerCards":{"0":[6,7,8,14,30],"1":[20,29,38,44]},"playedPlayerCards":[0,1,2,4,5,9,10,11,15,16,17,18,19,22,23,25,26,27,28,31,32,33,34,35,39,40,42,45,46],"insufficientPlayerCards":false},"pValues":[0.11125845930429169,0.1113520482257625,0.11120857044394132,0.11120857044394132,0.11089248905039104,0.11082274428528684,0.11126817668640185,0.11112383138188682,0.11086511017809655],"action":{"type":"DIRECT_FLIGHT","player":1,"from":18,"to":44,"card":44}},{"state":{"currentPlayer":1,"currentMovesLeft":1,"curedDiseases":[],"playerPosition":{"0":27,"1":44},"researchCenters":[3],"playerCards":{"0":[6,7,8,14,30],"1":[20,29,38]},"playedPlayerCards":[0,1,2,4,5,9,10,11,15,16,17,18,19,22,23,25,26,27,28,31,32,33,34,35,39,40,42,44,45,46],"insufficientPlayerCards":false},"pValues":[0.14298138784591533,0.14285896893920555,0.14263311048500682,0.14299201887654533,0.14220976090937298,0.14327054030640213,0.14305421263755194],"action":{"type":"DIRECT_FLIGHT","player":1,"from":44,"to":20,"card":20}},{"state":{"currentPlayer":0,"currentMovesLeft":4,"curedDiseases":[],"playerPosition":{"0":27,"1":20},"researchCenters":[3],"playerCards":{"0":[6,7,8,14,30],"1":[3,13,29,38]},"playedPlayerCards":[0,1,2,4,5,9,10,11,15,16,17,18,19,20,22,23,25,26,27,28,31,32,33,34,35,39,40,42,44,45,46],"insufficientPlayerCards":false},"pValues":[0.090901575678011,0.09092648518958713,0.09091411488993473,0.0908225153660294,0.090901575678011,0.09088886285272182,0.09088886285272182,0.09099740051879518,0.09099740051879518,0.0908225153660294,0.0909386910893633],"action":{"type":"DO_NOTHING","player":0}},{"state":{"currentPlayer":0,"currentMovesLeft":3,"curedDiseases":[],"playerPosition":{"0":27,"1":20},"researchCenters":[3],"playerCards":{"0":[6,7,8,14,30],"1":[3,13,29,38]},"playedPlayerCards":[0,1,2,4,5,9,10,11,15,16,17,18,19,20,22,23,25,26,27,28,31,32,33,34,35,39,40,42,44,45,46],"insufficientPlayerCards":false},"pValues":[0.0909542085472536,0.0909758679128383,0.09087410657242949,0.09078634020854671,0.09088598648622334,0.09081228463408499,0.0909542085472536,0.0909542085472536,0.09098650910881144,0.09086207088805136,0.0909542085472536],"action":{"type":"DRIVE_FERRY","player":0,"from":27,"to":35}},{"state":{"currentPlayer":0,"currentMovesLeft":2,"curedDiseases":[],"playerPosition":{"0":35,"1":20},"researchCenters":[3],"playerCards":{"0":[6,7,8,14,30],"1":[3,13,29,38]},"playedPlayerCards":[0,1,2,4,5,9,10,11,15,16,17,18,19,20,22,23,25,26,27,28,31,32,33,34,35,39,40,42,44,45,46],"insufficientPlayerCards":false},"pValues":[0.10006115089053647,0.1000503339481766,0.09997118811575606,0.09984613930849556,0.09993527291213247,0.10000586969458301,0.10003939997411347,0.10009292404697771,0.09994738716105221,0.1000503339481766],"action":{"type":"DIRECT_FLIGHT","player":0,"from":35,"to":8,"card":8}},{"state":{"currentPlayer":0,"currentMovesLeft":1,"curedDiseases":[],"playerPosition":{"0":8,"1":20},"researchCenters":[3],"playerCards":{"0":[6,7,14,30],"1":[3,13,29,38]},"playedPlayerCards":[0,1,2,4,5,8,9,10,11,15,16,17,18,19,20,22,23,25,26,27,28,31,32,33,34,35,39,40,42,44,45,46],"insufficientPlayerCards":false},"pValues":[0.11125250241866667,0.11115934535171386,0.11121204986072288,0.11099706831962994,0.11086485136905568,0.11108113804347176,0.1113567787023494,0.11117008598749878,0.11090617994689107],"action":{"type":"DRIVE_FERRY","player":0,"from":8,"to":6}},{"state":{"currentPlayer":1,"currentMovesLeft":4,"curedDiseases":[],"playerPosition":{"0":6,"1":20},"researchCenters":[3],"playerCards":{"0":[6,7,14,30,36,43],"1":[3,13,29,38]},"playedPlayerCards":[0,1,2,4,5,8,9,10,11,15,16,17,18,19,20,22,23,25,26,27,28,31,32,33,34,35,39,40,42,44,45,46],"insufficientPlayerCards":false},"pValues":[0.10004502533744451,0.10009157712598356,0.09997091146346275,0.09998364759485631,0.09989092405535564,0.0998769540459689,0.09997091146346275,0.10008013861773737,0.1000330444715174,0.10005686582421087],"action":{"type":"DRIVE_FERRY","player":1,"from":20,"to":18}},{"state":{"currentPlayer":1,"currentMovesLeft":3,"curedDiseases":[],"playerPosition":{"0":6,"1":18},"researchCenters":[3],"playerCards":{"0":[6,7,14,30,36,43],"1":[3,13,29,38]},"playedPlayerCards":[0,1,2,4,5,8,9,10,11,15,16,17,18,19,20,22,23,25,26,27,28,31,32,33,34,35,39,40,42,44,45,46],"insufficientPlayerCards":false},"pValues":[0.11117257266919228,0.11115098717939413,0.11118321178312153,0.11116183179315799,0.110948519596287,0.11104836072920524,0.11121453748107532,0.11108362273555428,0.11103635603301222],"action":{"type":"DIRECT_FLIGHT","player":1,"from":18,"to":13,"card":13}},{"state":{"currentPlayer":1,"currentMovesLeft":2,"curedDiseases":[],"playerPosition":{"0":6,"1":13},"researchCenters":[3],"playerCards":{"0":[6,7,14,30,36,43],"1":[3,29,38]},"playedPlayerCards":[0,1,2,4,5,8,9,10,11,13,15,16,17,18,19,20,22,23,25,26,27,28,31,32,33,34,35,39,40,42,44,45,46],"insufficientPlayerCards":false},"pValues":[0.11111298390704777,0.11117712384597843,0.11112393162690101,0.11113477360094909,0.11115614838675335,0.11107948501731797,0.11107948501731797,0.11105658358041662,0.11107948501731797],"action":{"type":"DO_NOTHING","player":1}},{"state":{"currentPlayer":1,"currentMovesLeft":1,"curedDiseases":[],"playerPosition":{"0":6,"1":13},"researchCenters":[3],"playerCards":{"0":[6,7,14,30,36,43],"1":[3,29,38]},"playedPlayerCards":[0,1,2,4,5,8,9,10,11,13,15,16,17,18,19,20,22,23,25,26,27,28,31,32,33,34,35,39,40,42,44,45,46],"insufficientPlayerCards":false},"pValues":[0.11127856434559479,0.11099372727349746,0.11095567507704163,0.11127856434559479,0.11111198020607219,0.11106616378682227,0.1107739811288657,0.111353426828823,0.11118791700768814],"action":{"type":"DIRECT_FLIGHT","player":1,"from":13,"to":38,"card":38}},{"state":{"currentPlayer":0,"currentMovesLeft":4,"curedDiseases":[],"playerPosition":{"0":6,"1":38},"researchCenters":[3],"playerCards":{"0":[6,7,14,30,36,43],"1":[3,24,29,37]},"playedPlayerCards":[0,1,2,4,5,8,9,10,11,13,15,16,17,18,19,20,22,23,25,26,27,28,31,32,33,34,35,38,39,40,42,44,45,46],"insufficientPlayerCards":false},"pValues":[0.016954404218727022,0.016954404218727022,0.016954404218727022,0.01694184430809214,0.016928289022910475,0.016954404218727022,0.016954404218727022,0.01694184430809214,0.016966105585131213,0.01694184430809214,0.016954404218727022,0.016954404218727022,0.016954404218727022,0.01694184430809214,0.016954404218727022,0.016954404218727022,0.016954404218727022,0.016954404218727022,0.016954404218727022,0.016954404218727022,0.016954404218727022,0.01694184430809214,0.016954404218727022,0.016954404218727022,0.016954404218727022,0.016954404218727022,0.016928289022910475,0.016954404218727022,0.016966105585131213,0.016966105585131213,0.016928289022910475,0.01694184430809214,0.016954404218727022,0.01694184430809214,0.01694184430809214,0.01694184430809214,0.01694184430809214,0.01694184430809214,0.016928289022910475,0.016954404218727022,0.016954404218727022,0.016954404218727022,0.016954404218727022,0.016954404218727022,0.016954404218727022,0.01694184430809214,0.01694184430809214,0.01694184430809214,0.016954404218727022,0.016954404218727022,0.01694184430809214,0.016954404218727022,0.01694184430809214,0.01694184430809214,0.016954404218727022,0.016928289022910475,0.016954404218727022,0.01694184430809214,0.016966105585131213],"action":{"type":"CHARTER_FLIGHT","player":0,"from":6,"to":38,"card":6}},{"state":{"currentPlayer":0,"currentMovesLeft":3,"curedDiseases":[],"playerPosition":{"0":38,"1":38},"researchCenters":[3],"playerCards":{"0":[7,14,30,36,43],"1":[3,24,29,37]},"playedPlayerCards":[0,1,2,4,5,6,8,9,10,11,13,15,16,17,18,19,20,22,23,25,26,27,28,31,32,33,34,35,38,39,40,42,44,45,46],"insufficientPlayerCards":false},"pValues":[0.10003359269755066,0.10004543183124602,0.10002161320073634,0.09987950902537751,0.09995948729292785,0.10011369434721688,0.09997222196890068,0.10006870196527529,0.09997222196890068,0.09993352570186806],"action":{"type":"DIRECT_FLIGHT","player":0,"from":38,"to":30,"card":30}},{"state":{"currentPlayer":0,"currentMovesLeft":2,"curedDiseases":[],"playerPosition":{"0":30,"1":38},"researchCenters":[3],"playerCards":{"0":[7,14,36,43],"1":[3,24,29,37]},"playedPlayerCards":[0,1,2,4,5,6,8,9,10,11,13,15,16,17,18,19,20,22,23,25,26,27,28,30,31,32,33,34,35,38,39,40,42,44,45,46],"insufficientPlayerCards":false},"pValues":[0.10000781507501767,0.1001042001292468,0.10011436359540271,0.10005179130014263,0.09991366484485659,0.09992592509620163,0.1001042001292468,0.09991366484485659,0.10004097536958555,0.09982339961544325],"action":{"type":"DIRECT_FLIGHT","player":0,"from":30,"to":14,"card":14}},{"state":{"currentPlayer":0,"currentMovesLeft":1,"curedDiseases":[],"playerPosition":{"0":14,"1":38},"researchCenters":[3],"playerCards":{"0":[7,36,43],"1":[3,24,29,37]},"playedPlayerCards":[0,1,2,4,5,6,8,9,10,11,13,14,15,16,17,18,19,20,22,23,25,26,27,28,30,31,32,33,34,35,38,39,40,42,44,45,46],"insufficientPlayerCards":false},"pValues":[0.14294792980736365,0.14308130164364266,0.1428245788500938,0.1426896864414499,0.14312948983092308,0.14263732698507708,0.1426896864414499],"action":{"type":"DIRECT_FLIGHT","player":0,"from":14,"to":36,"card":36}},{"state":{"currentPlayer":1,"currentMovesLeft":4,"curedDiseases":[],"playerPosition":{"0":36,"1":38},"researchCenters":[3],"playerCards":{"0":[7,12,41,43],"1":[3,24,29,37]},"playedPlayerCards":[0,1,2,4,5,6,8,9,10,11,13,14,15,16,17,18,19,20,22,23,25,26,27,28,30,31,32,33,34,35,36,38,39,40,42,44,45,46],"insufficientPlayerCards":false},"pValues":[0.110852298954749,0.11212332316319819,0.11081654281524705,0.1121003250595821,0.110852298954749,0.11070186199533262,0.11083456362742017,0.11092055830167936,0.11079822712804255],"action":{"type":"DRIVE_FERRY","player":1,"from":38,"to":3}},{"state":{"currentPlayer":1,"currentMovesLeft":3,"curedDiseases":[],"playerPosition":{"0":36,"1":3},"researchCenters":[3],"playerCards":{"0":[7,12,41,43],"1":[3,24,29,37]},"playedPlayerCards":[0,1,2,4,5,6,8,9,10,11,13,14,15,16,17,18,19,20,22,23,25,26,27,28,30,31,32,33,34,35,36,38,39,40,42,44,45,46],"insufficientPlayerCards":false},"pValues":[0.017860386874058935,0.017860386874058935,0.0178501810772297,0.0178792145865137,0.0178501810772297,0.0178501810772297,0.017860386874058935,0.0178501810772297,0.017860386874058935,0.0178501810772297,0.0178501810772297,0.0178501810772297,0.017860386874058935,0.0178501810772297,0.0178501810772297,0.0178501810772297,0.0178501810772297,0.0178501810772297,0.017860386874058935,0.0178501810772297,0.017860386874058935,0.0178501810772297,0.0178501810772297,0.0178501810772297,0.017860386874058935,0.017860386874058935,0.017860386874058935,0.0178501810772297,0.0178501810772297,0.0178501810772297,0.0178501810772297,0.0178501810772297,0.0178501810772297,0.0178501810772297,0.0178501810772297,0.0178501810772297,0.017860386874058935,0.017860386874058935,0.0178501810772297,0.0178501810772297,0.017860386874058935,0.0178501810772297,0.017860386874058935,0.0178501810772297,0.0178501810772297,0.017887940013064547,0.017860386874058935,0.017860386874058935,0.0178501810772297,0.0178501810772297,0.017860386874058935,0.0178501810772297,0.0178501810772297,0.017860386874058935,0.0178501810772297,0.01798954396432189],"action":{"type":"DIRECT_FLIGHT","player":1,"from":3,"to":37,"card":37}},{"state":{"currentPlayer":1,"currentMovesLeft":2,"curedDiseases":[],"playerPosition":{"0":36,"1":37},"researchCenters":[3],"playerCards":{"0":[7,12,41,43],"1":[3,24,29]},"playedPlayerCards":[0,1,2,4,5,6,8,9,10,11,13,14,15,16,17,18,19,20,22,23,25,26,27,28,30,31,32,33,34,35,36,37,38,39,40,42,44,45,46],"insufficientPlayerCards":false},"pValues":[0.11117493974102502,0.11118646116022703,0.11118646116022703,0.11101328940782794,0.11107824696804607,0.11105271354933309,0.11109079902508726,0.11106555289847098,0.11115153608975557],"action":{"type":"DIRECT_FLIGHT","player":1,"from":37,"to":3,"card":3}},{"state":{"currentPlayer":1,"currentMovesLeft":1,"curedDiseases":[],"playerPosition":{"0":36,"1":3},"researchCenters":[3],"playerCards":{"0":[7,12,41,43],"1":[24,29]},"playedPlayerCards":[0,1,2,3,4,5,6,8,9,10,11,13,14,15,16,17,18,19,20,22,23,25,26,27,28,30,31,32,33,34,35,36,37,38,39,40,42,44,45,46],"insufficientPlayerCards":false},"pValues":[0.16675565128263256,0.1668185972896242,0.16666788798496457,0.1665023482457111,0.16665658880688283,0.16659892639018475],"action":{"type":"DIRECT_FLIGHT","player":1,"from":3,"to":29,"card":29}}],"vValue":-1}}